LICENSE.rst
LICENSE_GPL.rst
MANIFEST.in
README.rst
setup.py
src/agx/__init__.py
src/agx.core.egg-info/PKG-INFO
src/agx.core.egg-info/SOURCES.txt
src/agx.core.egg-info/dependency_links.txt
src/agx.core.egg-info/namespace_packages.txt
src/agx.core.egg-info/not-zip-safe
src/agx.core.egg-info/requires.txt
src/agx.core.egg-info/top_level.txt
src/agx/core/__init__.py
src/agx/core/_api.py
src/agx/core/_api.rst
src/agx/core/config.py
src/agx/core/config.rst
src/agx/core/configure.zcml
src/agx/core/interfaces.py
src/agx/core/loader.py
src/agx/core/loginitializer.py
src/agx/core/main.py
src/agx/core/meta.zcml
src/agx/core/metaconfigure.py
src/agx/core/metadirectives.py
src/agx/core/postmortem.py
src/agx/core/test_metaconfigure.zcml
src/agx/core/tests.py
src/agx/core/util.py
src/agx/core/version.txt
src/agx/core/testing/__init__.py
src/agx/core/testing/mock.py