Metadata-Version: 1.1
Name: agx.core
Version: 1.0a2
Summary: AGX tree transformation chain processor
Home-page: http://github.com/bluedynamics/agx.core
Author: BlueDynamics Alliance
Author-email: dev@bluedynamics.com
License: GNU General Public Licence
Keywords: AGX,Code Generation
Platform: UNKNOWN
Classifier: Development Status :: 3 - Alpha
Classifier: License :: OSI Approved :: GNU General Public License (GPL)
Classifier: Programming Language :: Python
